LICENSE
README.md
setup.py
roombot/__init__.py
roombot.egg-info/PKG-INFO
roombot.egg-info/SOURCES.txt
roombot.egg-info/dependency_links.txt
roombot.egg-info/requires.txt
roombot.egg-info/top_level.txt