Metadata-Version: 2.1
Name: roombot
Version: 0.0.21
Summary: Mini framework for creating bots with tracking the user's position in the so-called "rooms". Based on aiogram.
Home-page: https://github.com/drogi17/roombot
Author: ic_it
Author-email: 
License: GNU 3
Platform: UNKNOWN
Classifier: Operating System :: OS Independent
Classifier: Intended Audience :: Developers
Classifier: Programming Language :: Python :: 3
Requires-Python: >=3.6
